<?xml version="1.0" encoding="utf-8"?>
<XnaContent xmlns:ns="Microsoft.Xna.Framework">
    <Asset Type="System.Collections.Generic.List[DataModels.TileLootData]">
        <Item>
            <TileId>5525</TileId>
            <Loot>
            <Item Type="DataModels.LootData">
            <ItemName>Stone</ItemName>
            <Quantity>1</Quantity>
            <Weight>100</Weight>
            </Item>
            </Loot>
        </Item>
          <Item>
            <TileId>5343</TileId>
            <Loot>
            <Item Type="DataModels.LootData">
            <ItemName>Pumpkin Chunk</ItemName>
            <Quantity>1</Quantity>
            <Weight>100</Weight>
            </Item>
            </Loot>
        </Item>
         <Item>
            <TileId>5434</TileId>
            <Loot>
            <Item Type="DataModels.LootData">
            <ItemName>Stone</ItemName>
            <Quantity>1</Quantity>
            <Weight>100</Weight>
            </Item>
            </Loot>
        </Item>
    </Asset>
</XnaContent>